melthon/__init__.py
melthon/__main__.py
melthon/cli.py
melthon/core.py
melthon/data.py
melthon/middleware.py
melthon/template.py
melthon-2.1.0.dist-info/AUTHORS.rst
melthon-2.1.0.dist-info/LICENSE
melthon-2.1.0.dist-info/METADATA
melthon-2.1.0.dist-info/WHEEL
melthon-2.1.0.dist-info/entry_points.txt
melthon-2.1.0.dist-info/top_level.txt
melthon-2.1.0.dist-info/RECORD
