Metadata-Version: 2.1
Name: melthon
Version: 2.1.0
Summary: Minimalistic static site generator
Home-page: https://github.com/jenswbe/python-melthon
Author: Jens Willemsens
Author-email: contact@jensw.be
License: GPLv3
Project-URL: Documentation, https://python-melthon.readthedocs.io/
Project-URL: Changelog, https://python-melthon.readthedocs.io/en/latest/changelog.html
Project-URL: Issue Tracker, https://github.com/jenswbe/python-melthon/issues
Platform: UNKNOWN
Classifier: Development Status :: 5 - Production/Stable
Classifier: Intended Audience :: Developers
Classifier: License :: OSI Approved :: GNU General Public License v3 (GPLv3)
Classifier: Operating System :: Unix
Classifier: Operating System :: POSIX
Classifier: Operating System :: Microsoft :: Windows
Classifier: Programming Language :: Python
Classifier: Programming Language :: Python :: 3.8
Classifier: Programming Language :: Python :: Implementation :: PyPy
Classifier: Topic :: Utilities
Requires-Python: ==3.8.*
Requires-Dist: click
Requires-Dist: dpath
Requires-Dist: mako
Requires-Dist: pyyaml
